crossover/__init__.py
crossover/xrequests.py
examples/__init__.py
examples/database.py
celery_crossover-1.1.16.dist-info/LICENSE.txt
celery_crossover-1.1.16.dist-info/METADATA
celery_crossover-1.1.16.dist-info/WHEEL
celery_crossover-1.1.16.dist-info/top_level.txt
celery_crossover-1.1.16.dist-info/RECORD
