Metadata-Version: 2.1
Name: celery-crossover
Version: 1.1.16
Summary: Celery Crossover aims to make it really easy to execute tasks in another service.
Home-page: https://github.com/debonzi/celery_crossover
Author: Daniel Debonzi
Author-email: debonzi@gmail.com
License: UNKNOWN
Platform: UNKNOWN
Classifier: Development Status :: 4 - Beta
Classifier: Intended Audience :: Developers
Classifier: Topic :: Software Development :: Object Brokering
Classifier: Programming Language :: Python :: 2.7
Classifier: Programming Language :: Python :: 3.5
Classifier: Programming Language :: Python :: 3.6
Classifier: Programming Language :: Python :: 3.7
Classifier: Programming Language :: Python :: 3.8
License-File: LICENSE.txt
Requires-Dist: celery[redis] (>=3.1.20)
Requires-Dist: requests-celery-adapters (>=2.0.14)
Requires-Dist: six (>=1.11.0)
Provides-Extra: ci
Requires-Dist: python-coveralls ; extra == 'ci'
Provides-Extra: dev
Requires-Dist: pytest ; extra == 'dev'
Requires-Dist: pytest-cov ; extra == 'dev'
Requires-Dist: tox ; extra == 'dev'
Requires-Dist: black ; extra == 'dev'
Provides-Extra: test
Requires-Dist: pytest ; extra == 'test'
Requires-Dist: pytest-cov ; extra == 'test'
Requires-Dist: tox ; extra == 'test'
